pyevolution/__init__.py
pyevolution/envs/__init__.py
pyevolution/envs/prima_vita/__init__.py
pyevolution/envs/prima_vita/global_constants.py
pyevolution/envs/prima_vita/particle_class.py
pyevolution/envs/prima_vita/player_class.py
pyevolution/envs/prima_vita/prima_vita.py
pyevolution/envs/prima_vita/images/dead-player.png
pyevolution/envs/prima_vita/images/food.png
pyevolution/envs/prima_vita/images/food_near.png
pyevolution/envs/prima_vita/images/player.png
pyevolution/envs/prima_vita/images/player_mating.png
pyevolution/envs/prima_vita/images/player_near.png
pyevolution/models/__init__.py
pyevolution/models/reinforce/__init__.py
pyevolution/models/reinforce/reinforce.py
pyevolution/models/reinforce/reinforce_nn.py
pyevolution-0.1.0.dist-info/METADATA
pyevolution-0.1.0.dist-info/WHEEL
pyevolution-0.1.0.dist-info/top_level.txt
pyevolution-0.1.0.dist-info/RECORD
