Metadata-Version: 2.1
Name: pyevolution
Version: 0.1.0
Summary: PyTorch based framework for training artificial agents in bio-inspired environments
Home-page: https://github.com/Project-DC/pyevolve
Author: Siddhartha Dhar Choudhury
Author-email: sdharchou@gmail.com
License: GNU General Public License v3
Platform: UNKNOWN
Classifier: License :: OSI Approved :: GNU General Public License v3 (GPLv3)
Classifier: Programming Language :: Python :: 3
Classifier: Programming Language :: Python :: 3.9
Classifier: Programming Language :: Python :: 3.8
Classifier: Programming Language :: Python :: 3.7
Classifier: Programming Language :: Python :: 3.6
Requires-Dist: pygame
Requires-Dist: numpy
Requires-Dist: torch
